Metadata-Version: 2.1
Name: inject-globals
Version: 1.0.0.4
Summary: A decorator for injecting global variables into function calls.
Home-page: https://github.com/victorwss/inject-globals
Author: Victor Williams Stafusa da Silva
Author-email: victorwssilva@gmail.com
License: UNKNOWN
Platform: UNKNOWN
Classifier: Programming Language :: Python :: 3
Classifier: License :: OSI Approved :: MIT License
Classifier: Operating System :: OS Independent
